sf_rotation/__init__.py
sf_rotation/__main__.py
sf_rotation/hevo_client.py
sf_rotation/key_generator.py
sf_rotation/main.py
sf_rotation/snowflake_client.py
sf_rotation/utils.py
sf_rotation-1.3.3.dist-info/licenses/LICENSE
sf_rotation-1.3.3.dist-info/METADATA
sf_rotation-1.3.3.dist-info/WHEEL
sf_rotation-1.3.3.dist-info/entry_points.txt
sf_rotation-1.3.3.dist-info/top_level.txt
sf_rotation-1.3.3.dist-info/RECORD
