Metadata-Version: 2.4
Name: sf-rotation
Version: 1.3.3
Summary: Snowflake Key Pair Rotation Tool for Hevo Data destinations
License: MIT
Project-URL: Homepage, https://github.com/Legolasan/sf_rotation
Project-URL: Repository, https://github.com/Legolasan/sf_rotation
Project-URL: Issues, https://github.com/Legolasan/sf_rotation/issues
Keywords: snowflake,hevo,key-pair,rotation,authentication
Classifier: Development Status :: 4 - Beta
Classifier: Intended Audience :: Developers
Classifier: Intended Audience :: System Administrators
Classifier: License :: OSI Approved :: MIT License
Classifier: Operating System :: OS Independent
Classifier: Programming Language :: Python :: 3
Classifier: Programming Language :: Python :: 3.8
Classifier: Programming Language :: Python :: 3.9
Classifier: Programming Language :: Python :: 3.10
Classifier: Programming Language :: Python :: 3.11
Classifier: Programming Language :: Python :: 3.12
Classifier: Topic :: Database
Classifier: Topic :: Security
Requires-Python: >=3.8
License-File: LICENSE
Requires-Dist: snowflake-connector-python>=3.0.0
Requires-Dist: requests>=2.28.0
Requires-Dist: PyYAML>=6.0
Provides-Extra: dev
Requires-Dist: pytest>=7.0.0; extra == "dev"
Requires-Dist: black>=23.0.0; extra == "dev"
Requires-Dist: flake8>=6.0.0; extra == "dev"
Dynamic: license-file
